kotlin_style_check
