Metadata-Version: 2.1
Name: kotlin-style-check
Version: 1.0
Summary: Library that provides ability to fix naming and comments in Kotlin code files according to Kotlin code conventions
Home-page: https://github.com/Vermillio/Metaprogramming2.0
Author: Vermillio
Author-email: morganas.scream@gmail.com
License: MIT
Keywords: code conventions,formatting,naming,Kotlin,C#,lexical analysis,parsing
Platform: UNKNOWN
Classifier: Development Status :: 3 - Alpha
Classifier: Intended Audience :: Developers
Classifier: License :: OSI Approved :: MIT License
Requires-Python: >=3.6
